{
  "@context": "http://iiif.io/api/presentation/2/context.json",
  "@id": "https://princetongenizalab.github.io/iiif/jrl/a/a-1468.json",
  "@type": "sc:Manifest",
  "label": "JRL SERIES A 1468",
  "metadata": [
    {
      "label": "Provenance",
      "value": "Remixed IIIF manifests generated by the Center for Digital Humanities at Princeton and the Princeton Geniza Lab from <a href=\"https://luna.manchester.ac.uk/luna/servlet/ManchesterDev~95~2\">University of Manchester Genizah Collection</a>."
    }
  ],
  "description": "Torat ha-Bayit",
  "rendering": {
    "@id": "https://luna.manchester.ac.uk/luna/servlet/view/search?q=reference_number%3D%22A+1468%22+LIMIT%3AManchesterDev~95~&sort=reference_number%2Cdate_created",
    "format": "text/html"
  },
  "attribution": "Image rights: The University of Manchester Library. Access rights: CC BY-NC-SA 4.0",
  "license": "http://creativecommons.org/licenses/by-nc-sa/4.0/",
  "logo": "https://princetongenizalab.github.io/iiif/jrl/umanchester_logo.png",
  "viewingHint": "individuals",
  "sequences": [
    {
      "@type": "sc:Sequence",
      "canvases": [
        {
          "@id": "https://luna.manchester.ac.uk/luna/servlet/iiif/m/ManchesterDev~95~2~25306~112697/canvas/c1",
          "@type": "sc:Canvas",
          "label": "1 / 3 leaves, recto",
          "height": 5350,
          "width": 4017,
          "images": [
            {
              "@type": "oa:Annotation",
              "motivation": "sc:painting",
              "resource": {
                "@id": "https://luna.manchester.ac.uk/luna/servlet/iiif/ManchesterDev~95~2~25306~112697/full/full/0/default.jpg",
                "@type": "dctypes:Image",
                "format": "image/jpeg",
                "height": 5350,
                "width": 4017,
                "service": {
                  "@context": "http://iiif.io/api/image/2/context.json",
                  "@id": "https://luna.manchester.ac.uk/luna/servlet/iiif/ManchesterDev~95~2~25306~112697",
                  "profile": "http://iiif.io/api/image/2/level0.json"
                }
              },
              "on": "https://luna.manchester.ac.uk/luna/servlet/iiif/m/ManchesterDev~95~2~25306~112697/canvas/c1"
            }
          ],
          "partOf": [
            {
              "@id": "https://luna.manchester.ac.uk/luna/servlet/iiif/m/ManchesterDev~95~2~25306~112697/manifest",
              "@type": "sc:Manifest",
              "label": {
                "en": [
                  "original source: A 1468 - 1"
                ]
              }
            }
          ]
        },
        {
          "@id": "https://luna.manchester.ac.uk/luna/servlet/iiif/m/ManchesterDev~95~2~25312~112698/canvas/c1",
          "@type": "sc:Canvas",
          "label": "1 / 3 leaves, verso",
          "height": 5350,
          "width": 4017,
          "images": [
            {
              "@type": "oa:Annotation",
              "motivation": "sc:painting",
              "resource": {
                "@id": "https://luna.manchester.ac.uk/luna/servlet/iiif/ManchesterDev~95~2~25312~112698/full/full/0/default.jpg",
                "@type": "dctypes:Image",
                "format": "image/jpeg",
                "height": 5350,
                "width": 4017,
                "service": {
                  "@context": "http://iiif.io/api/image/2/context.json",
                  "@id": "https://luna.manchester.ac.uk/luna/servlet/iiif/ManchesterDev~95~2~25312~112698",
                  "profile": "http://iiif.io/api/image/2/level0.json"
                }
              },
              "on": "https://luna.manchester.ac.uk/luna/servlet/iiif/m/ManchesterDev~95~2~25312~112698/canvas/c1"
            }
          ],
          "partOf": [
            {
              "@id": "https://luna.manchester.ac.uk/luna/servlet/iiif/m/ManchesterDev~95~2~25312~112698/manifest",
              "@type": "sc:Manifest",
              "label": {
                "en": [
                  "original source: A 1468 - 2"
                ]
              }
            }
          ]
        },
        {
          "@id": "https://luna.manchester.ac.uk/luna/servlet/iiif/m/ManchesterDev~95~2~25318~112699/canvas/c1",
          "@type": "sc:Canvas",
          "label": "2 / 3 leaves, recto",
          "height": 5350,
          "width": 4017,
          "images": [
            {
              "@type": "oa:Annotation",
              "motivation": "sc:painting",
              "resource": {
                "@id": "https://luna.manchester.ac.uk/luna/servlet/iiif/ManchesterDev~95~2~25318~112699/full/full/0/default.jpg",
                "@type": "dctypes:Image",
                "format": "image/jpeg",
                "height": 5350,
                "width": 4017,
                "service": {
                  "@context": "http://iiif.io/api/image/2/context.json",
                  "@id": "https://luna.manchester.ac.uk/luna/servlet/iiif/ManchesterDev~95~2~25318~112699",
                  "profile": "http://iiif.io/api/image/2/level0.json"
                }
              },
              "on": "https://luna.manchester.ac.uk/luna/servlet/iiif/m/ManchesterDev~95~2~25318~112699/canvas/c1"
            }
          ],
          "partOf": [
            {
              "@id": "https://luna.manchester.ac.uk/luna/servlet/iiif/m/ManchesterDev~95~2~25318~112699/manifest",
              "@type": "sc:Manifest",
              "label": {
                "en": [
                  "original source: A 1468 - 3"
                ]
              }
            }
          ]
        },
        {
          "@id": "https://luna.manchester.ac.uk/luna/servlet/iiif/m/ManchesterDev~95~2~25324~112700/canvas/c1",
          "@type": "sc:Canvas",
          "label": "2 / 3 leaves, verso",
          "height": 5350,
          "width": 4017,
          "images": [
            {
              "@type": "oa:Annotation",
              "motivation": "sc:painting",
              "resource": {
                "@id": "https://luna.manchester.ac.uk/luna/servlet/iiif/ManchesterDev~95~2~25324~112700/full/full/0/default.jpg",
                "@type": "dctypes:Image",
                "format": "image/jpeg",
                "height": 5350,
                "width": 4017,
                "service": {
                  "@context": "http://iiif.io/api/image/2/context.json",
                  "@id": "https://luna.manchester.ac.uk/luna/servlet/iiif/ManchesterDev~95~2~25324~112700",
                  "profile": "http://iiif.io/api/image/2/level0.json"
                }
              },
              "on": "https://luna.manchester.ac.uk/luna/servlet/iiif/m/ManchesterDev~95~2~25324~112700/canvas/c1"
            }
          ],
          "partOf": [
            {
              "@id": "https://luna.manchester.ac.uk/luna/servlet/iiif/m/ManchesterDev~95~2~25324~112700/manifest",
              "@type": "sc:Manifest",
              "label": {
                "en": [
                  "original source: A 1468 - 4"
                ]
              }
            }
          ]
        },
        {
          "@id": "https://luna.manchester.ac.uk/luna/servlet/iiif/m/ManchesterDev~95~2~25330~112701/canvas/c1",
          "@type": "sc:Canvas",
          "label": "3 / 3 leaves, recto",
          "height": 5350,
          "width": 4017,
          "images": [
            {
              "@type": "oa:Annotation",
              "motivation": "sc:painting",
              "resource": {
                "@id": "https://luna.manchester.ac.uk/luna/servlet/iiif/ManchesterDev~95~2~25330~112701/full/full/0/default.jpg",
                "@type": "dctypes:Image",
                "format": "image/jpeg",
                "height": 5350,
                "width": 4017,
                "service": {
                  "@context": "http://iiif.io/api/image/2/context.json",
                  "@id": "https://luna.manchester.ac.uk/luna/servlet/iiif/ManchesterDev~95~2~25330~112701",
                  "profile": "http://iiif.io/api/image/2/level0.json"
                }
              },
              "on": "https://luna.manchester.ac.uk/luna/servlet/iiif/m/ManchesterDev~95~2~25330~112701/canvas/c1"
            }
          ],
          "partOf": [
            {
              "@id": "https://luna.manchester.ac.uk/luna/servlet/iiif/m/ManchesterDev~95~2~25330~112701/manifest",
              "@type": "sc:Manifest",
              "label": {
                "en": [
                  "original source: A 1468 - 5"
                ]
              }
            }
          ]
        },
        {
          "@id": "https://luna.manchester.ac.uk/luna/servlet/iiif/m/ManchesterDev~95~2~25336~112702/canvas/c1",
          "@type": "sc:Canvas",
          "label": "3 / 3 leaves, verso",
          "height": 5350,
          "width": 4017,
          "images": [
            {
              "@type": "oa:Annotation",
              "motivation": "sc:painting",
              "resource": {
                "@id": "https://luna.manchester.ac.uk/luna/servlet/iiif/ManchesterDev~95~2~25336~112702/full/full/0/default.jpg",
                "@type": "dctypes:Image",
                "format": "image/jpeg",
                "height": 5350,
                "width": 4017,
                "service": {
                  "@context": "http://iiif.io/api/image/2/context.json",
                  "@id": "https://luna.manchester.ac.uk/luna/servlet/iiif/ManchesterDev~95~2~25336~112702",
                  "profile": "http://iiif.io/api/image/2/level0.json"
                }
              },
              "on": "https://luna.manchester.ac.uk/luna/servlet/iiif/m/ManchesterDev~95~2~25336~112702/canvas/c1"
            }
          ],
          "partOf": [
            {
              "@id": "https://luna.manchester.ac.uk/luna/servlet/iiif/m/ManchesterDev~95~2~25336~112702/manifest",
              "@type": "sc:Manifest",
              "label": {
                "en": [
                  "original source: A 1468 - 6"
                ]
              }
            }
          ]
        }
      ]
    }
  ]
}